logdecorator/__init__.py
logdecorator/asyncio.py
logdecorator/decorator.py
logdecorator/tests.py
logdecorator-2.2.dist-info/DESCRIPTION.rst
logdecorator-2.2.dist-info/METADATA
logdecorator-2.2.dist-info/RECORD
logdecorator-2.2.dist-info/WHEEL
logdecorator-2.2.dist-info/metadata.json
logdecorator-2.2.dist-info/top_level.txt
