Metadata-Version: 2.0
Name: logdecorator
Version: 2.2
Summary: Move logging code out of your business logic with decorators
Home-page: https://github.com/sighalt/logdecorator
Author: Jakob Rößler
Author-email: roessler@sighalt.de
License: UNKNOWN
Keywords: logging,decorators,clean code
Platform: UNKNOWN
Classifier: Intended Audience :: Developers
Classifier: License :: OSI Approved :: MIT License
Classifier: Topic :: Software Development
Classifier: Topic :: Software Development :: Libraries
Classifier: Topic :: System :: Logging
